MacPackageTest/__init__.py
MacPackageTest/main.py
MacPackageTest-0.1.dist-info/DESCRIPTION.rst
MacPackageTest-0.1.dist-info/METADATA
MacPackageTest-0.1.dist-info/RECORD
MacPackageTest-0.1.dist-info/WHEEL
MacPackageTest-0.1.dist-info/metadata.json
MacPackageTest-0.1.dist-info/top_level.txt
Package_Test/__init__.py
Package_Test/main.py
