Metadata-Version: 2.0
Name: MacPackageTest
Version: 0.1
Summary: MacPackageTest
Home-page: UNKNOWN
Author: UNKNOWN
Author-email: UNKNOWN
License: UNKNOWN
Platform: UNKNOWN
